pybodytrack/BodyTracking.py
pybodytrack/__init__.py
pybodytrack/bodyparts/__init__.py
pybodytrack/bodyparts/body_parts.py
pybodytrack/enums/PoseProcessor.py
pybodytrack/enums/VideoMode.py
pybodytrack/enums/__init__.py
pybodytrack/methods/__init__.py
pybodytrack/methods/methods.py
pybodytrack/observer/Message.py
pybodytrack/observer/Observer.py
pybodytrack/observer/__init__.py
pybodytrack/pose_estimators/__init__.py
pybodytrack/pose_estimators/mediapipe_processor.py
pybodytrack/pose_estimators/openpose_processor.py
pybodytrack/pose_estimators/yolo_processor.py
pybodytrack/posetracker/__init__.py
pybodytrack/posetracker/pose_tracker.py
pybodytrack/utils/__init__.py
pybodytrack/utils/utils.py
pybodytrack-2025.3.3.dist-info/LICENSE
pybodytrack-2025.3.3.dist-info/METADATA
pybodytrack-2025.3.3.dist-info/WHEEL
pybodytrack-2025.3.3.dist-info/top_level.txt
pybodytrack-2025.3.3.dist-info/RECORD
